packagingapi/__init__.py
packagingapi/packagingapi.py
packagingapi-1.1.2.dist-info/METADATA
packagingapi-1.1.2.dist-info/WHEEL
packagingapi-1.1.2.dist-info/top_level.txt
packagingapi-1.1.2.dist-info/RECORD
