Metadata-Version: 2.1
Name: packagingapi
Version: 1.1.2
Summary: Test Package
Author: jiminlee
Author-email: jimin.lee@nota.ai
Requires-Python: >=3
Requires-Dist: requests
Requires-Dist: polling2
Requires-Dist: urllib3
Requires-Dist: mock
Requires-Dist: click
